trytond/modules/akademy_company/LICENSE
trytond/modules/akademy_company/README.md
trytond/modules/akademy_company/__init__.py
trytond/modules/akademy_company/company.py
trytond/modules/akademy_company/company.xml
trytond/modules/akademy_company/party.py
trytond/modules/akademy_company/report.py
trytond/modules/akademy_company/report.xml
trytond/modules/akademy_company/tryton.cfg
trytond/modules/akademy_company/locale/en.po
trytond/modules/akademy_company/locale/fr.po
trytond/modules/akademy_company/locale/pt.po
trytond/modules/akademy_company/reports/company.fodt
trytond/modules/akademy_company/reports/employee.fodt
trytond/modules/akademy_company/reports/student.fodt
trytond/modules/akademy_company/security/access_rights_admin.xml
trytond/modules/akademy_company/security/access_rights_direct.xml
trytond/modules/akademy_company/security/access_rights_secret.xml
trytond/modules/akademy_company/security/access_rights_student.xml
trytond/modules/akademy_company/security/access_rights_teacher.xml
trytond/modules/akademy_company/tests/__init__.py
trytond/modules/akademy_company/tests/test_company.py
trytond/modules/akademy_company/view/company_form.xml
trytond/modules/akademy_company/view/employee_form.xml
trytond/modules/akademy_company/view/employee_list.xml
trytond/modules/akademy_company/view/student_form.xml
trytond/modules/akademy_company/view/student_list.xml
trytond/modules/akademy_company/view/student_supervisor_form.xml
trytond/modules/akademy_company/view/student_supervisor_list.xml
akademy_company-1.1.0.dist-info/METADATA
akademy_company-1.1.0.dist-info/WHEEL
akademy_company-1.1.0.dist-info/licenses/LICENSE
akademy_company-1.1.0.dist-info/RECORD
