Metadata-Version: 2.4
Name: akademy_company
Version: 1.1.0
Summary: SAGE Education is a free and open-source project for educators, educational institutions, and governments.
Project-URL: Homepage, https://comunidadedosaber.ao
Project-URL: Documentation, https://docs.comunidadedosaber.ao
Project-URL: Demo, https://sage.comunidadedosaber.ao
Project-URL: Repository, https://github.com/zacariasjuliano/akademy-company
Project-URL: Bug Tracker, https://github.com/zacariasjuliano/akademy-company/issues
Project-URL: Changelog, https://github.com/zacariasjuliano/akademy-company/blob/main/CHANGELOG.md
Author-email: Zacarias Juliano Capingala <zacariasjuliano@gmail.com>
License: GPL-3.0-or-later
License-File: LICENSE
Requires-Python: >=3.8
Requires-Dist: akademy-party~=1.1
Requires-Dist: trytond-company==7.0
